{
    "sourceFile": ".gitignore",
    "activeCommit": 0,
    "commits": [
        {
            "activePatchIndex": 1,
            "patches": [
                {
                    "date": 1685467222274,
                    "content": "Index: \n===================================================================\n--- \n+++ \n"
                },
                {
                    "date": 1685467464808,
                    "content": "Index: \n===================================================================\n--- \n+++ \n@@ -13,5 +13,5 @@\n \n # Avoid your project being littered with annoying .DS_Store files!\n .DS_Store\n .prettierignore\n-README-template.md\n\\ No newline at end of file\n+.README-template.md\n\\ No newline at end of file\n"
                }
            ],
            "date": 1685467222274,
            "name": "Commit-0",
            "content": "# Avoid accidental upload of the Sketch and Figma design files\n#####################################################\n## Please do not remove lines 5 and 6 - thanks! 🙂 ##\n#####################################################\n*.sketch\n*.fig\n\n# Avoid accidental XD upload if you convert the design file\n###############################################\n## Please do not remove line 12 - thanks! 🙂 ##\n###############################################\n*.xd\n\n# Avoid your project being littered with annoying .DS_Store files!\n.DS_Store\n.prettierignore\nREADME-template.md"
        }
    ]
}